repo_scaffold/__init__.py
repo_scaffold/cli.py
repo_scaffold/templates/cookiecutter.json
repo_scaffold/templates/template-python/cookiecutter.json
repo_scaffold/templates/template-python/hooks/__init__.py
repo_scaffold/templates/template-python/hooks/post_gen_project.py
repo_scaffold/templates/template-python/{{cookiecutter.project_slug}}/.cz.yaml
repo_scaffold/templates/template-python/{{cookiecutter.project_slug}}/.dockerignore
repo_scaffold/templates/template-python/{{cookiecutter.project_slug}}/.gitignore
repo_scaffold/templates/template-python/{{cookiecutter.project_slug}}/.pre-commit-config.yaml
repo_scaffold/templates/template-python/{{cookiecutter.project_slug}}/.ruff.toml
repo_scaffold/templates/template-python/{{cookiecutter.project_slug}}/.yamlfmt.yaml
repo_scaffold/templates/template-python/{{cookiecutter.project_slug}}/README.md
repo_scaffold/templates/template-python/{{cookiecutter.project_slug}}/Taskfile.yml
repo_scaffold/templates/template-python/{{cookiecutter.project_slug}}/mkdocs.yml
repo_scaffold/templates/template-python/{{cookiecutter.project_slug}}/pyproject.toml
repo_scaffold/templates/template-python/{{cookiecutter.project_slug}}/.github/workflows/ci-tests.yaml
repo_scaffold/templates/template-python/{{cookiecutter.project_slug}}/.github/workflows/container-release.yaml
repo_scaffold/templates/template-python/{{cookiecutter.project_slug}}/.github/workflows/docs-deploy.yaml
repo_scaffold/templates/template-python/{{cookiecutter.project_slug}}/.github/workflows/package-release.yaml
repo_scaffold/templates/template-python/{{cookiecutter.project_slug}}/.github/workflows/version-bump.yaml
repo_scaffold/templates/template-python/{{cookiecutter.project_slug}}/.vscode/settings.json
repo_scaffold/templates/template-python/{{cookiecutter.project_slug}}/container/Dockerfile
repo_scaffold/templates/template-python/{{cookiecutter.project_slug}}/container/compose.yaml
repo_scaffold-0.13.5.dist-info/METADATA
repo_scaffold-0.13.5.dist-info/WHEEL
repo_scaffold-0.13.5.dist-info/entry_points.txt
repo_scaffold-0.13.5.dist-info/RECORD
