Metadata-Version: 2.4
Name: repo-scaffold
Version: 0.13.5
Summary: shawn deng repo temple project
Author-email: shawndeng <shawndeng1109@qq.com>
License-Expression: MIT
Requires-Python: >=3.12
Requires-Dist: click>=8.1.8
Requires-Dist: cookiecutter>=2.6.0
Requires-Dist: ruff>=0.9.6
Provides-Extra: dev
Requires-Dist: commitizen>=3.12.0; extra == 'dev'
Requires-Dist: pytest-cov>=6.0.0; extra == 'dev'
Requires-Dist: pytest-mock>=3.14.0; extra == 'dev'
Requires-Dist: pytest>=8.3.4; extra == 'dev'
Requires-Dist: ruff>=0.9.7; extra == 'dev'
Provides-Extra: docs
Requires-Dist: mkdocs-gen-files>=0.5.0; extra == 'docs'
Requires-Dist: mkdocs-literate-nav>=0.6.1; extra == 'docs'
Requires-Dist: mkdocs-material>=9.5.3; extra == 'docs'
Requires-Dist: mkdocs>=1.5.3; extra == 'docs'
Requires-Dist: mkdocstrings-python>=1.7.5; extra == 'docs'
Requires-Dist: mkdocstrings>=0.24.0; extra == 'docs'
Requires-Dist: pymdown-extensions>=10.7; extra == 'docs'
